[
  {
    "params": {
      "lr": 1e-05,
      "batch_size": 4,
      "epochs": 2
    },
    "result": {
      "job_id": "grid_search_1",
      "status": "failed",
      "duration": 12.524650812149048,
      "output": "[20:10:32] [INFO] ============================================================\n[20:10:32] [INFO] AUTOMATED TRAINING & PROMOTION PIPELINE\n[20:10:32] [INFO] ============================================================\n[20:10:32] [INFO] Config: {\n  \"max_train_samples\": 500,\n  \"max_eval_samples\": 100,\n  \"epochs\": 2,\n  \"dataset\": \"datasets/chat/mixed_chat\",\n  \"device\": \"auto\"\n}\n[20:10:32] [INFO] ============================================================\n[20:10:32] [INFO] Starting training phase...\n[20:10:32] [INFO] Training command: C:\\Users\\Bryan\\AppData\\Local\\Programs\\Python\\Python311\\python.exe C:\\Users\\Bryan\\OneDrive\\AI\\AI\\microsoft_phi-silica-3.6_v1\\scripts\\train_lora.py --dataset datasets/chat/mixed_chat --max-train-samples 500 --max-eval-samples 100 --epochs 2 --device auto --learning-rate 1e-05 --per-device-train-batch-size 4\n[20:10:44] [ERROR] Training failed after 12.3s\n[20:10:44] [ERROR] Error: usage: train_lora.py [-h] [--config CONFIG] [--dataset DATASET] [--dry-run]\n                     [--max-train-samples MAX_TRAIN_SAMPLES]\n                     [--max-eval-samples MAX_EVAL_SAMPLES]\n                     [--hf-model-id HF_MODEL_ID] [--no-stream]\n                     [--deepspeed DEEPSPEED] [--train-manifest TRAIN_MANIFEST]\n                     [--eval-manifest EVAL_MANIFEST] [--save-dir SAVE_DIR]\n                     [--device {auto,cuda,cpu,directml,mps}]\n                     [--learning-rate LEARNING_RATE]\n                     [--lora-dropout LORA_DROPOUT] [--epochs EPOCHS]\n                     [--train-batch-size TRAIN_BATCH_SIZE]\n                     [--eval-batch-size EVAL_BATCH_SIZE] [--seed SEED]\ntrain_lora.py: error: unrecognized arguments: --per-device-train-batch-size 4\n\n[20:10:44] [ERROR] Training failed, aborting pipeline\n"
    }
  },
  {
    "params": {
      "lr": 1e-05,
      "batch_size": 4,
      "epochs": 3
    },
    "result": {
      "job_id": "grid_search_2",
      "status": "failed",
      "duration": 11.862622022628784,
      "output": "[20:10:44] [INFO] ============================================================\n[20:10:44] [INFO] AUTOMATED TRAINING & PROMOTION PIPELINE\n[20:10:44] [INFO] ============================================================\n[20:10:44] [INFO] Config: {\n  \"max_train_samples\": 500,\n  \"max_eval_samples\": 100,\n  \"epochs\": 3,\n  \"dataset\": \"datasets/chat/mixed_chat\",\n  \"device\": \"auto\"\n}\n[20:10:44] [INFO] ============================================================\n[20:10:44] [INFO] Starting training phase...\n[20:10:44] [INFO] Training command: C:\\Users\\Bryan\\AppData\\Local\\Programs\\Python\\Python311\\python.exe C:\\Users\\Bryan\\OneDrive\\AI\\AI\\microsoft_phi-silica-3.6_v1\\scripts\\train_lora.py --dataset datasets/chat/mixed_chat --max-train-samples 500 --max-eval-samples 100 --epochs 3 --device auto --learning-rate 1e-05 --per-device-train-batch-size 4\n[20:10:56] [ERROR] Training failed after 11.7s\n[20:10:56] [ERROR] Error: usage: train_lora.py [-h] [--config CONFIG] [--dataset DATASET] [--dry-run]\n                     [--max-train-samples MAX_TRAIN_SAMPLES]\n                     [--max-eval-samples MAX_EVAL_SAMPLES]\n                     [--hf-model-id HF_MODEL_ID] [--no-stream]\n                     [--deepspeed DEEPSPEED] [--train-manifest TRAIN_MANIFEST]\n                     [--eval-manifest EVAL_MANIFEST] [--save-dir SAVE_DIR]\n                     [--device {auto,cuda,cpu,directml,mps}]\n                     [--learning-rate LEARNING_RATE]\n                     [--lora-dropout LORA_DROPOUT] [--epochs EPOCHS]\n                     [--train-batch-size TRAIN_BATCH_SIZE]\n                     [--eval-batch-size EVAL_BATCH_SIZE] [--seed SEED]\ntrain_lora.py: error: unrecognized arguments: --per-device-train-batch-size 4\n\n[20:10:56] [ERROR] Training failed, aborting pipeline\n"
    }
  },
  {
    "params": {
      "lr": 1e-05,
      "batch_size": 8,
      "epochs": 2
    },
    "result": {
      "job_id": "grid_search_3",
      "status": "failed",
      "duration": 12.224701881408691,
      "output": "[20:10:56] [INFO] ============================================================\n[20:10:56] [INFO] AUTOMATED TRAINING & PROMOTION PIPELINE\n[20:10:56] [INFO] ============================================================\n[20:10:56] [INFO] Config: {\n  \"max_train_samples\": 500,\n  \"max_eval_samples\": 100,\n  \"epochs\": 2,\n  \"dataset\": \"datasets/chat/mixed_chat\",\n  \"device\": \"auto\"\n}\n[20:10:56] [INFO] ============================================================\n[20:10:56] [INFO] Starting training phase...\n[20:10:56] [INFO] Training command: C:\\Users\\Bryan\\AppData\\Local\\Programs\\Python\\Python311\\python.exe C:\\Users\\Bryan\\OneDrive\\AI\\AI\\microsoft_phi-silica-3.6_v1\\scripts\\train_lora.py --dataset datasets/chat/mixed_chat --max-train-samples 500 --max-eval-samples 100 --epochs 2 --device auto --learning-rate 1e-05 --per-device-train-batch-size 8\n[20:11:08] [ERROR] Training failed after 12.0s\n[20:11:08] [ERROR] Error: usage: train_lora.py [-h] [--config CONFIG] [--dataset DATASET] [--dry-run]\n                     [--max-train-samples MAX_TRAIN_SAMPLES]\n                     [--max-eval-samples MAX_EVAL_SAMPLES]\n                     [--hf-model-id HF_MODEL_ID] [--no-stream]\n                     [--deepspeed DEEPSPEED] [--train-manifest TRAIN_MANIFEST]\n                     [--eval-manifest EVAL_MANIFEST] [--save-dir SAVE_DIR]\n                     [--device {auto,cuda,cpu,directml,mps}]\n                     [--learning-rate LEARNING_RATE]\n                     [--lora-dropout LORA_DROPOUT] [--epochs EPOCHS]\n                     [--train-batch-size TRAIN_BATCH_SIZE]\n                     [--eval-batch-size EVAL_BATCH_SIZE] [--seed SEED]\ntrain_lora.py: error: unrecognized arguments: --per-device-train-batch-size 8\n\n[20:11:08] [ERROR] Training failed, aborting pipeline\n"
    }
  },
  {
    "params": {
      "lr": 1e-05,
      "batch_size": 8,
      "epochs": 3
    },
    "result": {
      "job_id": "grid_search_4",
      "status": "failed",
      "duration": 12.757569313049316,
      "output": "[20:11:09] [INFO] ============================================================\n[20:11:09] [INFO] AUTOMATED TRAINING & PROMOTION PIPELINE\n[20:11:09] [INFO] ============================================================\n[20:11:09] [INFO] Config: {\n  \"max_train_samples\": 500,\n  \"max_eval_samples\": 100,\n  \"epochs\": 3,\n  \"dataset\": \"datasets/chat/mixed_chat\",\n  \"device\": \"auto\"\n}\n[20:11:09] [INFO] ============================================================\n[20:11:09] [INFO] Starting training phase...\n[20:11:09] [INFO] Training command: C:\\Users\\Bryan\\AppData\\Local\\Programs\\Python\\Python311\\python.exe C:\\Users\\Bryan\\OneDrive\\AI\\AI\\microsoft_phi-silica-3.6_v1\\scripts\\train_lora.py --dataset datasets/chat/mixed_chat --max-train-samples 500 --max-eval-samples 100 --epochs 3 --device auto --learning-rate 1e-05 --per-device-train-batch-size 8\n[20:11:21] [ERROR] Training failed after 12.5s\n[20:11:21] [ERROR] Error: usage: train_lora.py [-h] [--config CONFIG] [--dataset DATASET] [--dry-run]\n                     [--max-train-samples MAX_TRAIN_SAMPLES]\n                     [--max-eval-samples MAX_EVAL_SAMPLES]\n                     [--hf-model-id HF_MODEL_ID] [--no-stream]\n                     [--deepspeed DEEPSPEED] [--train-manifest TRAIN_MANIFEST]\n                     [--eval-manifest EVAL_MANIFEST] [--save-dir SAVE_DIR]\n                     [--device {auto,cuda,cpu,directml,mps}]\n                     [--learning-rate LEARNING_RATE]\n                     [--lora-dropout LORA_DROPOUT] [--epochs EPOCHS]\n                     [--train-batch-size TRAIN_BATCH_SIZE]\n                     [--eval-batch-size EVAL_BATCH_SIZE] [--seed SEED]\ntrain_lora.py: error: unrecognized arguments: --per-device-train-batch-size 8\n\n[20:11:21] [ERROR] Training failed, aborting pipeline\n"
    }
  },
  {
    "params": {
      "lr": 2e-05,
      "batch_size": 4,
      "epochs": 2
    },
    "result": {
      "job_id": "grid_search_5",
      "status": "failed",
      "duration": 11.525299310684204,
      "output": "[20:11:21] [INFO] ============================================================\n[20:11:21] [INFO] AUTOMATED TRAINING & PROMOTION PIPELINE\n[20:11:21] [INFO] ============================================================\n[20:11:21] [INFO] Config: {\n  \"max_train_samples\": 500,\n  \"max_eval_samples\": 100,\n  \"epochs\": 2,\n  \"dataset\": \"datasets/chat/mixed_chat\",\n  \"device\": \"auto\"\n}\n[20:11:21] [INFO] ============================================================\n[20:11:21] [INFO] Starting training phase...\n[20:11:21] [INFO] Training command: C:\\Users\\Bryan\\AppData\\Local\\Programs\\Python\\Python311\\python.exe C:\\Users\\Bryan\\OneDrive\\AI\\AI\\microsoft_phi-silica-3.6_v1\\scripts\\train_lora.py --dataset datasets/chat/mixed_chat --max-train-samples 500 --max-eval-samples 100 --epochs 2 --device auto --learning-rate 2e-05 --per-device-train-batch-size 4\n[20:11:33] [ERROR] Training failed after 11.3s\n[20:11:33] [ERROR] Error: usage: train_lora.py [-h] [--config CONFIG] [--dataset DATASET] [--dry-run]\n                     [--max-train-samples MAX_TRAIN_SAMPLES]\n                     [--max-eval-samples MAX_EVAL_SAMPLES]\n                     [--hf-model-id HF_MODEL_ID] [--no-stream]\n                     [--deepspeed DEEPSPEED] [--train-manifest TRAIN_MANIFEST]\n                     [--eval-manifest EVAL_MANIFEST] [--save-dir SAVE_DIR]\n                     [--device {auto,cuda,cpu,directml,mps}]\n                     [--learning-rate LEARNING_RATE]\n                     [--lora-dropout LORA_DROPOUT] [--epochs EPOCHS]\n                     [--train-batch-size TRAIN_BATCH_SIZE]\n                     [--eval-batch-size EVAL_BATCH_SIZE] [--seed SEED]\ntrain_lora.py: error: unrecognized arguments: --per-device-train-batch-size 4\n\n[20:11:33] [ERROR] Training failed, aborting pipeline\n"
    }
  },
  {
    "params": {
      "lr": 2e-05,
      "batch_size": 4,
      "epochs": 3
    },
    "result": {
      "job_id": "grid_search_6",
      "status": "failed",
      "duration": 11.355990886688232,
      "output": "[20:11:33] [INFO] ============================================================\n[20:11:33] [INFO] AUTOMATED TRAINING & PROMOTION PIPELINE\n[20:11:33] [INFO] ============================================================\n[20:11:33] [INFO] Config: {\n  \"max_train_samples\": 500,\n  \"max_eval_samples\": 100,\n  \"epochs\": 3,\n  \"dataset\": \"datasets/chat/mixed_chat\",\n  \"device\": \"auto\"\n}\n[20:11:33] [INFO] ============================================================\n[20:11:33] [INFO] Starting training phase...\n[20:11:33] [INFO] Training command: C:\\Users\\Bryan\\AppData\\Local\\Programs\\Python\\Python311\\python.exe C:\\Users\\Bryan\\OneDrive\\AI\\AI\\microsoft_phi-silica-3.6_v1\\scripts\\train_lora.py --dataset datasets/chat/mixed_chat --max-train-samples 500 --max-eval-samples 100 --epochs 3 --device auto --learning-rate 2e-05 --per-device-train-batch-size 4\n[20:11:44] [ERROR] Training failed after 11.2s\n[20:11:44] [ERROR] Error: usage: train_lora.py [-h] [--config CONFIG] [--dataset DATASET] [--dry-run]\n                     [--max-train-samples MAX_TRAIN_SAMPLES]\n                     [--max-eval-samples MAX_EVAL_SAMPLES]\n                     [--hf-model-id HF_MODEL_ID] [--no-stream]\n                     [--deepspeed DEEPSPEED] [--train-manifest TRAIN_MANIFEST]\n                     [--eval-manifest EVAL_MANIFEST] [--save-dir SAVE_DIR]\n                     [--device {auto,cuda,cpu,directml,mps}]\n                     [--learning-rate LEARNING_RATE]\n                     [--lora-dropout LORA_DROPOUT] [--epochs EPOCHS]\n                     [--train-batch-size TRAIN_BATCH_SIZE]\n                     [--eval-batch-size EVAL_BATCH_SIZE] [--seed SEED]\ntrain_lora.py: error: unrecognized arguments: --per-device-train-batch-size 4\n\n[20:11:44] [ERROR] Training failed, aborting pipeline\n"
    }
  },
  {
    "params": {
      "lr": 2e-05,
      "batch_size": 8,
      "epochs": 2
    },
    "result": {
      "job_id": "grid_search_7",
      "status": "failed",
      "duration": 12.24660611152649,
      "output": "[20:11:44] [INFO] ============================================================\n[20:11:44] [INFO] AUTOMATED TRAINING & PROMOTION PIPELINE\n[20:11:44] [INFO] ============================================================\n[20:11:44] [INFO] Config: {\n  \"max_train_samples\": 500,\n  \"max_eval_samples\": 100,\n  \"epochs\": 2,\n  \"dataset\": \"datasets/chat/mixed_chat\",\n  \"device\": \"auto\"\n}\n[20:11:44] [INFO] ============================================================\n[20:11:44] [INFO] Starting training phase...\n[20:11:44] [INFO] Training command: C:\\Users\\Bryan\\AppData\\Local\\Programs\\Python\\Python311\\python.exe C:\\Users\\Bryan\\OneDrive\\AI\\AI\\microsoft_phi-silica-3.6_v1\\scripts\\train_lora.py --dataset datasets/chat/mixed_chat --max-train-samples 500 --max-eval-samples 100 --epochs 2 --device auto --learning-rate 2e-05 --per-device-train-batch-size 8\n[20:11:56] [ERROR] Training failed after 12.1s\n[20:11:56] [ERROR] Error: usage: train_lora.py [-h] [--config CONFIG] [--dataset DATASET] [--dry-run]\n                     [--max-train-samples MAX_TRAIN_SAMPLES]\n                     [--max-eval-samples MAX_EVAL_SAMPLES]\n                     [--hf-model-id HF_MODEL_ID] [--no-stream]\n                     [--deepspeed DEEPSPEED] [--train-manifest TRAIN_MANIFEST]\n                     [--eval-manifest EVAL_MANIFEST] [--save-dir SAVE_DIR]\n                     [--device {auto,cuda,cpu,directml,mps}]\n                     [--learning-rate LEARNING_RATE]\n                     [--lora-dropout LORA_DROPOUT] [--epochs EPOCHS]\n                     [--train-batch-size TRAIN_BATCH_SIZE]\n                     [--eval-batch-size EVAL_BATCH_SIZE] [--seed SEED]\ntrain_lora.py: error: unrecognized arguments: --per-device-train-batch-size 8\n\n[20:11:56] [ERROR] Training failed, aborting pipeline\n"
    }
  },
  {
    "params": {
      "lr": 2e-05,
      "batch_size": 8,
      "epochs": 3
    },
    "result": {
      "job_id": "grid_search_8",
      "status": "failed",
      "duration": 11.52794075012207,
      "output": "[20:11:56] [INFO] ============================================================\n[20:11:56] [INFO] AUTOMATED TRAINING & PROMOTION PIPELINE\n[20:11:56] [INFO] ============================================================\n[20:11:56] [INFO] Config: {\n  \"max_train_samples\": 500,\n  \"max_eval_samples\": 100,\n  \"epochs\": 3,\n  \"dataset\": \"datasets/chat/mixed_chat\",\n  \"device\": \"auto\"\n}\n[20:11:56] [INFO] ============================================================\n[20:11:56] [INFO] Starting training phase...\n[20:11:56] [INFO] Training command: C:\\Users\\Bryan\\AppData\\Local\\Programs\\Python\\Python311\\python.exe C:\\Users\\Bryan\\OneDrive\\AI\\AI\\microsoft_phi-silica-3.6_v1\\scripts\\train_lora.py --dataset datasets/chat/mixed_chat --max-train-samples 500 --max-eval-samples 100 --epochs 3 --device auto --learning-rate 2e-05 --per-device-train-batch-size 8\n[20:12:08] [ERROR] Training failed after 11.3s\n[20:12:08] [ERROR] Error: usage: train_lora.py [-h] [--config CONFIG] [--dataset DATASET] [--dry-run]\n                     [--max-train-samples MAX_TRAIN_SAMPLES]\n                     [--max-eval-samples MAX_EVAL_SAMPLES]\n                     [--hf-model-id HF_MODEL_ID] [--no-stream]\n                     [--deepspeed DEEPSPEED] [--train-manifest TRAIN_MANIFEST]\n                     [--eval-manifest EVAL_MANIFEST] [--save-dir SAVE_DIR]\n                     [--device {auto,cuda,cpu,directml,mps}]\n                     [--learning-rate LEARNING_RATE]\n                     [--lora-dropout LORA_DROPOUT] [--epochs EPOCHS]\n                     [--train-batch-size TRAIN_BATCH_SIZE]\n                     [--eval-batch-size EVAL_BATCH_SIZE] [--seed SEED]\ntrain_lora.py: error: unrecognized arguments: --per-device-train-batch-size 8\n\n[20:12:08] [ERROR] Training failed, aborting pipeline\n"
    }
  },
  {
    "params": {
      "lr": 5e-05,
      "batch_size": 4,
      "epochs": 2
    },
    "result": {
      "job_id": "grid_search_9",
      "status": "failed",
      "duration": 11.789468050003052,
      "output": "[20:12:08] [INFO] ============================================================\n[20:12:08] [INFO] AUTOMATED TRAINING & PROMOTION PIPELINE\n[20:12:08] [INFO] ============================================================\n[20:12:08] [INFO] Config: {\n  \"max_train_samples\": 500,\n  \"max_eval_samples\": 100,\n  \"epochs\": 2,\n  \"dataset\": \"datasets/chat/mixed_chat\",\n  \"device\": \"auto\"\n}\n[20:12:08] [INFO] ============================================================\n[20:12:08] [INFO] Starting training phase...\n[20:12:08] [INFO] Training command: C:\\Users\\Bryan\\AppData\\Local\\Programs\\Python\\Python311\\python.exe C:\\Users\\Bryan\\OneDrive\\AI\\AI\\microsoft_phi-silica-3.6_v1\\scripts\\train_lora.py --dataset datasets/chat/mixed_chat --max-train-samples 500 --max-eval-samples 100 --epochs 2 --device auto --learning-rate 5e-05 --per-device-train-batch-size 4\n[20:12:20] [ERROR] Training failed after 11.6s\n[20:12:20] [ERROR] Error: usage: train_lora.py [-h] [--config CONFIG] [--dataset DATASET] [--dry-run]\n                     [--max-train-samples MAX_TRAIN_SAMPLES]\n                     [--max-eval-samples MAX_EVAL_SAMPLES]\n                     [--hf-model-id HF_MODEL_ID] [--no-stream]\n                     [--deepspeed DEEPSPEED] [--train-manifest TRAIN_MANIFEST]\n                     [--eval-manifest EVAL_MANIFEST] [--save-dir SAVE_DIR]\n                     [--device {auto,cuda,cpu,directml,mps}]\n                     [--learning-rate LEARNING_RATE]\n                     [--lora-dropout LORA_DROPOUT] [--epochs EPOCHS]\n                     [--train-batch-size TRAIN_BATCH_SIZE]\n                     [--eval-batch-size EVAL_BATCH_SIZE] [--seed SEED]\ntrain_lora.py: error: unrecognized arguments: --per-device-train-batch-size 4\n\n[20:12:20] [ERROR] Training failed, aborting pipeline\n"
    }
  },
  {
    "params": {
      "lr": 5e-05,
      "batch_size": 4,
      "epochs": 3
    },
    "result": {
      "job_id": "grid_search_10",
      "status": "failed",
      "duration": 12.341896772384644,
      "output": "[20:12:20] [INFO] ============================================================\n[20:12:20] [INFO] AUTOMATED TRAINING & PROMOTION PIPELINE\n[20:12:20] [INFO] ============================================================\n[20:12:20] [INFO] Config: {\n  \"max_train_samples\": 500,\n  \"max_eval_samples\": 100,\n  \"epochs\": 3,\n  \"dataset\": \"datasets/chat/mixed_chat\",\n  \"device\": \"auto\"\n}\n[20:12:20] [INFO] ============================================================\n[20:12:20] [INFO] Starting training phase...\n[20:12:20] [INFO] Training command: C:\\Users\\Bryan\\AppData\\Local\\Programs\\Python\\Python311\\python.exe C:\\Users\\Bryan\\OneDrive\\AI\\AI\\microsoft_phi-silica-3.6_v1\\scripts\\train_lora.py --dataset datasets/chat/mixed_chat --max-train-samples 500 --max-eval-samples 100 --epochs 3 --device auto --learning-rate 5e-05 --per-device-train-batch-size 4\n[20:12:32] [ERROR] Training failed after 12.1s\n[20:12:32] [ERROR] Error: usage: train_lora.py [-h] [--config CONFIG] [--dataset DATASET] [--dry-run]\n                     [--max-train-samples MAX_TRAIN_SAMPLES]\n                     [--max-eval-samples MAX_EVAL_SAMPLES]\n                     [--hf-model-id HF_MODEL_ID] [--no-stream]\n                     [--deepspeed DEEPSPEED] [--train-manifest TRAIN_MANIFEST]\n                     [--eval-manifest EVAL_MANIFEST] [--save-dir SAVE_DIR]\n                     [--device {auto,cuda,cpu,directml,mps}]\n                     [--learning-rate LEARNING_RATE]\n                     [--lora-dropout LORA_DROPOUT] [--epochs EPOCHS]\n                     [--train-batch-size TRAIN_BATCH_SIZE]\n                     [--eval-batch-size EVAL_BATCH_SIZE] [--seed SEED]\ntrain_lora.py: error: unrecognized arguments: --per-device-train-batch-size 4\n\n[20:12:32] [ERROR] Training failed, aborting pipeline\n"
    }
  },
  {
    "params": {
      "lr": 5e-05,
      "batch_size": 8,
      "epochs": 2
    },
    "result": {
      "job_id": "grid_search_11",
      "status": "failed",
      "duration": 12.120392560958862,
      "output": "[20:12:32] [INFO] ============================================================\n[20:12:32] [INFO] AUTOMATED TRAINING & PROMOTION PIPELINE\n[20:12:32] [INFO] ============================================================\n[20:12:32] [INFO] Config: {\n  \"max_train_samples\": 500,\n  \"max_eval_samples\": 100,\n  \"epochs\": 2,\n  \"dataset\": \"datasets/chat/mixed_chat\",\n  \"device\": \"auto\"\n}\n[20:12:32] [INFO] ============================================================\n[20:12:32] [INFO] Starting training phase...\n[20:12:32] [INFO] Training command: C:\\Users\\Bryan\\AppData\\Local\\Programs\\Python\\Python311\\python.exe C:\\Users\\Bryan\\OneDrive\\AI\\AI\\microsoft_phi-silica-3.6_v1\\scripts\\train_lora.py --dataset datasets/chat/mixed_chat --max-train-samples 500 --max-eval-samples 100 --epochs 2 --device auto --learning-rate 5e-05 --per-device-train-batch-size 8\n[20:12:44] [ERROR] Training failed after 11.9s\n[20:12:44] [ERROR] Error: usage: train_lora.py [-h] [--config CONFIG] [--dataset DATASET] [--dry-run]\n                     [--max-train-samples MAX_TRAIN_SAMPLES]\n                     [--max-eval-samples MAX_EVAL_SAMPLES]\n                     [--hf-model-id HF_MODEL_ID] [--no-stream]\n                     [--deepspeed DEEPSPEED] [--train-manifest TRAIN_MANIFEST]\n                     [--eval-manifest EVAL_MANIFEST] [--save-dir SAVE_DIR]\n                     [--device {auto,cuda,cpu,directml,mps}]\n                     [--learning-rate LEARNING_RATE]\n                     [--lora-dropout LORA_DROPOUT] [--epochs EPOCHS]\n                     [--train-batch-size TRAIN_BATCH_SIZE]\n                     [--eval-batch-size EVAL_BATCH_SIZE] [--seed SEED]\ntrain_lora.py: error: unrecognized arguments: --per-device-train-batch-size 8\n\n[20:12:44] [ERROR] Training failed, aborting pipeline\n"
    }
  },
  {
    "params": {
      "lr": 5e-05,
      "batch_size": 8,
      "epochs": 3
    },
    "result": {
      "job_id": "grid_search_12",
      "status": "failed",
      "duration": 12.253804683685303,
      "output": "[20:12:44] [INFO] ============================================================\n[20:12:44] [INFO] AUTOMATED TRAINING & PROMOTION PIPELINE\n[20:12:44] [INFO] ============================================================\n[20:12:44] [INFO] Config: {\n  \"max_train_samples\": 500,\n  \"max_eval_samples\": 100,\n  \"epochs\": 3,\n  \"dataset\": \"datasets/chat/mixed_chat\",\n  \"device\": \"auto\"\n}\n[20:12:44] [INFO] ============================================================\n[20:12:44] [INFO] Starting training phase...\n[20:12:44] [INFO] Training command: C:\\Users\\Bryan\\AppData\\Local\\Programs\\Python\\Python311\\python.exe C:\\Users\\Bryan\\OneDrive\\AI\\AI\\microsoft_phi-silica-3.6_v1\\scripts\\train_lora.py --dataset datasets/chat/mixed_chat --max-train-samples 500 --max-eval-samples 100 --epochs 3 --device auto --learning-rate 5e-05 --per-device-train-batch-size 8\n[20:12:56] [ERROR] Training failed after 12.1s\n[20:12:56] [ERROR] Error: usage: train_lora.py [-h] [--config CONFIG] [--dataset DATASET] [--dry-run]\n                     [--max-train-samples MAX_TRAIN_SAMPLES]\n                     [--max-eval-samples MAX_EVAL_SAMPLES]\n                     [--hf-model-id HF_MODEL_ID] [--no-stream]\n                     [--deepspeed DEEPSPEED] [--train-manifest TRAIN_MANIFEST]\n                     [--eval-manifest EVAL_MANIFEST] [--save-dir SAVE_DIR]\n                     [--device {auto,cuda,cpu,directml,mps}]\n                     [--learning-rate LEARNING_RATE]\n                     [--lora-dropout LORA_DROPOUT] [--epochs EPOCHS]\n                     [--train-batch-size TRAIN_BATCH_SIZE]\n                     [--eval-batch-size EVAL_BATCH_SIZE] [--seed SEED]\ntrain_lora.py: error: unrecognized arguments: --per-device-train-batch-size 8\n\n[20:12:56] [ERROR] Training failed, aborting pipeline\n"
    }
  }
]